css_ciphers/__init__.py
css_ciphers/codes.py
css_ciphers-1.0.0.dist-info/licenses/LICENSE
css_ciphers-1.0.0.dist-info/METADATA
css_ciphers-1.0.0.dist-info/WHEEL
css_ciphers-1.0.0.dist-info/top_level.txt
css_ciphers-1.0.0.dist-info/RECORD
