Metadata-Version: 2.4
Name: css-ciphers
Version: 1.0.0
Summary: Functions that print CSS code snippets.
Author-email: Swaroop Vaze <vazeswaroop@gmail.com>
License: MIT License
Project-URL: Homepage, https://pypi.org/project/css-ciphers/
Classifier: Programming Language :: Python :: 3
Classifier: License :: OSI Approved :: MIT License
Classifier: Operating System :: OS Independent
Requires-Python: >=3.8
License-File: LICENSE
Dynamic: license-file
